[{"Name": "AB", "Code": "Alberta"}, {"Name": "AK", "Code": "Alaska"}, {"Name": "AL", "Code": "Alabama"}, {"Name": "AR", "Code": "Arkansas"}, {"Name": "AS", "Code": "American Samoa"}, {"Name": "AZ", "Code": "Arizona"}, {"Name": "BC", "Code": "British Columbia"}, {"Name": "CA", "Code": "California"}, {"Name": "CO", "Code": "Colorado"}, {"Name": "CT", "Code": "Connecticut"}, {"Name": "DC", "Code": "District of Columbia"}, {"Name": "DE", "Code": "Delaware"}, {"Name": "FL", "Code": "Florida"}, {"Name": "FM", "Code": "Federated States of Micronesia"}, {"Name": "GA", "Code": "Georgia"}, {"Name": "HI", "Code": "Hawaii"}, {"Name": "IA", "Code": "Iowa"}, {"Name": "ID", "Code": "Idaho"}, {"Name": "IL", "Code": "Illinois"}, {"Name": "IN", "Code": "Indiana"}, {"Name": "KS", "Code": "Kansas"}, {"Name": "KY", "Code": "Kentucky"}, {"Name": "LA", "Code": "Louisiana"}, {"Name": "MA", "Code": "Massachusetts"}, {"Name": "MB", "Code": "Manitoba"}, {"Name": "MD", "Code": "Maryland"}, {"Name": "ME", "Code": "Maine"}, {"Name": "MH", "Code": "Marshall Islands"}, {"Name": "MI", "Code": "Michigan"}, {"Name": "MN", "Code": "Minnesota"}, {"Name": "MO", "Code": "Missouri"}, {"Name": "MP", "Code": "Northern Mariana Islands"}, {"Name": "MS", "Code": "Mississippi"}, {"Name": "MT", "Code": "Montana"}, {"Name": "NB", "Code": "New Brunswick"}, {"Name": "NC", "Code": "North Carolina"}, {"Name": "ND", "Code": "North Dakota"}, {"Name": "NE", "Code": "Nebraska"}, {"Name": "NH", "Code": "New Hampshire"}, {"Name": "NJ", "Code": "New Jersey"}, {"Name": "NL", "Code": "Newfoundland and Labrador"}, {"Name": "NM", "Code": "New Mexico"}, {"Name": "NS", "Code": "Nova Scotia"}, {"Name": "NT", "Code": "Northwest Territories"}, {"Name": "NU", "Code": "Nunavut"}, {"Name": "NV", "Code": "Nevada"}, {"Name": "NY", "Code": "New York"}, {"Name": "OH", "Code": "Ohio"}, {"Name": "OK", "Code": "Oklahoma"}, {"Name": "ON", "Code": "Ontario"}, {"Name": "OR", "Code": "Oregon"}, {"Name": "PA", "Code": "Pennsylvania"}, {"Name": "PE", "Code": "Prince Edward Island"}, {"Name": "PR", "Code": "Puerto Rico"}, {"Name": "PW", "Code": "Palau"}, {"Name": "QC", "Code": "Quebec"}, {"Name": "RI", "Code": "Rhode Island"}, {"Name": "SC", "Code": "South Carolina"}, {"Name": "SD", "Code": "South Dakota"}, {"Name": "SK", "Code": "Saskatchewan"}, {"Name": "TN", "Code": "Tennessee"}, {"Name": "TX", "Code": "Texas"}, {"Name": "UT", "Code": "Utah"}, {"Name": "VA", "Code": "Virginia"}, {"Name": "VI", "Code": "Virgin Islands"}, {"Name": "VT", "Code": "Vermont"}, {"Name": "WA", "Code": "Washington"}, {"Name": "WI", "Code": "Wisconsin"}, {"Name": "WV", "Code": "West Virginia"}, {"Name": "WY", "Code": "Wyoming"}, {"Name": "YT", "Code": "Yukon"}, {"Name": "AE", "Code": "Armed Forces (Canada, Europe, Middle East)"}, {"Name": "AA", "Code": "Armed Forces (Americas)"}, {"Name": "AP", "Code": "Armed Forces (Pacific)"}]